{
	"info": {
		"_postman_id": "21f3a0fb-1fdd-421b-9e38-02f06adf7578",
		"name": "jdbc_auth",
		"schema": "https://schema.getpostman.com/json/collection/v2.1.0/collection.json"
	},
	"item": [
		{
			"name": "http://localhost:8080/test",
			"request": {
				"method": "GET",
				"header": [],
				"url": {
					"raw": "http://localhost:8080/test",
					"protocol": "http",
					"host": [
						"localhost"
					],
					"port": "8080",
					"path": [
						"test"
					]
				}
			},
			"response": []
		},
		{
			"name": "http://localhost:8080/login?username=user&password=123",
			"request": {
				"method": "POST",
				"header": [],
				"url": {
					"raw": "http://localhost:8080/login?username=user&password=123",
					"protocol": "http",
					"host": [
						"localhost"
					],
					"port": "8080",
					"path": [
						"login"
					],
					"query": [
						{
							"key": "username",
							"value": "user"
						},
						{
							"key": "password",
							"value": "123"
						}
					]
				}
			},
			"response": []
		},
		{
			"name": "http://localhost:8080/test",
			"request": {
				"method": "GET",
				"header": [],
				"url": {
					"raw": "http://localhost:8080/test",
					"protocol": "http",
					"host": [
						"localhost"
					],
					"port": "8080",
					"path": [
						"test"
					]
				}
			},
			"response": []
		},
		{
			"name": "http://localhost:8080/logout",
			"request": {
				"method": "GET",
				"header": [],
				"url": {
					"raw": "http://localhost:8080/logout",
					"protocol": "http",
					"host": [
						"localhost"
					],
					"port": "8080",
					"path": [
						"logout"
					]
				}
			},
			"response": []
		},
		{
			"name": "http://localhost:8080/test",
			"request": {
				"method": "GET",
				"header": [],
				"url": {
					"raw": "http://localhost:8080/test",
					"protocol": "http",
					"host": [
						"localhost"
					],
					"port": "8080",
					"path": [
						"test"
					]
				}
			},
			"response": []
		}
	],
	"protocolProfileBehavior": {}
}